{
    "POOL A": {
        "round 1-4": [
            [
                {
                    "country": "ESP",
                    "name": "Malin WILSON CLARET"
                },
                {
                    "winner": "Malin WILSON CLARET"
                }
            ],
            [
                {
                    "country": "USA",
                    "name": "Leana NELSON"
                },
                {
                    "country": "GEO",
                    "name": "Nino TSIKLAURI"
                },
                {
                    "winner": "Nino TSIKLAURI"
                }
            ],
            [
                {
                    "country": "FRA",
                    "name": "Alya DE CARVALHO"
                },
                {
                    "country": "FIN",
                    "name": "Pihla MATIKAINEN"
                },
                {
                    "winner": "Alya DE CARVALHO"
                }
            ],
            [
                {
                    "country": "ITA",
                    "name": "Giulia CAGGIANO"
                },
                {
                    "country": "ESP",
                    "name": "Andrea INSUA IGLESIAS"
                },
                {
                    "winner": "Giulia CAGGIANO"
                }
            ]
        ],
        "round 1-2": [
            [
                {
                    "country": "ESP",
                    "name": "Malin WILSON CLARET"
                },
                {
                    "country": "GEO",
                    "name": "Nino TSIKLAURI"
                },
                {
                    "winner": "Malin WILSON CLARET"
                }
            ],
            [
                {
                    "country": "FRA",
                    "name": "Alya DE CARVALHO"
                },
                {
                    "country": "ITA",
                    "name": "Giulia CAGGIANO"
                },
                {
                    "winner": "Alya DE CARVALHO"
                }
            ]
        ],
        "round 1-1": [
            [
                {
                    "country": "ESP",
                    "name": "Malin WILSON CLARET"
                },
                {
                    "country": "FRA",
                    "name": "Alya DE CARVALHO"
                }
            ]
        ],
        "final_winner": "Malin WILSON CLARET"
    },
    "POOL B": {
        "round 1-4": [
            [
                {
                    "country": "SLO",
                    "name": "Nika TOMC"
                },
                {
                    "winner": "Nika TOMC"
                }
            ],
            [
                {
                    "country": "UKR",
                    "name": "Alina SHYLOVA"
                },
                {
                    "country": "AUT",
                    "name": "Verena HIDEN"
                },
                {
                    "winner": "Verena HIDEN"
                }
            ],
            [
                {
                    "country": "RSA",
                    "name": "Donne BREYTENBACH"
                },
                {
                    "country": "CRO",
                    "name": "Dora BORTAS"
                },
                {
                    "winner": "Dora BORTAS"
                }
            ],
            [
                {
                    "country": "ESP",
                    "name": "Iratxe GARCIA PONCE"
                },
                {
                    "country": "HUN",
                    "name": "Kitti KOVACS"
                },
                {
                    "winner": "Kitti KOVACS"
                }
            ]
        ],
        "round 1-2": [
            [
                {
                    "country": "SLO",
                    "name": "Nika TOMC"
                },
                {
                    "country": "AUT",
                    "name": "Verena HIDEN"
                },
                {
                    "winner": "Nika TOMC"
                }
            ],
            [
                {
                    "country": "CRO",
                    "name": "Dora BORTAS"
                },
                {
                    "country": "HUN",
                    "name": "Kitti KOVACS"
                },
                {
                    "winner": "Kitti KOVACS"
                }
            ]
        ],
        "round 1-1": [
            [
                {
                    "country": "SLO",
                    "name": "Nika TOMC"
                },
                {
                    "country": "HUN",
                    "name": "Kitti KOVACS"
                }
            ]
        ],
        "final_winner": "Nika TOMC"
    },
    "POOL C": {
        "round 1-4": [
            [
                {
                    "country": "GEO",
                    "name": "Nino LOLADZE"
                },
                {
                    "winner": "Nino LOLADZE"
                }
            ],
            [
                {
                    "country": "CAN",
                    "name": "Kelly DEGUCHI"
                },
                {
                    "country": "SUI",
                    "name": "Binta NDIAYE"
                },
                {
                    "winner": "Binta NDIAYE"
                }
            ],
            [
                {
                    "country": "SLO",
                    "name": "Jevgenija GAJIC"
                },
                {
                    "country": "UKR",
                    "name": "Inna SHYNKARENKO"
                },
                {
                    "winner": "Inna SHYNKARENKO"
                }
            ],
            [
                {
                    "country": "ESP",
                    "name": "Adriana RODRIGUEZ SALVADOR"
                },
                {
                    "country": "NED",
                    "name": "Danique JANSSEN"
                },
                {
                    "winner": "Adriana RODRIGUEZ SALVADOR"
                }
            ]
        ],
        "round 1-2": [
            [
                {
                    "country": "GEO",
                    "name": "Nino LOLADZE"
                },
                {
                    "country": "SUI",
                    "name": "Binta NDIAYE"
                },
                {
                    "winner": "Binta NDIAYE"
                }
            ],
            [
                {
                    "country": "UKR",
                    "name": "Inna SHYNKARENKO"
                },
                {
                    "country": "ESP",
                    "name": "Adriana RODRIGUEZ SALVADOR"
                },
                {
                    "winner": "Adriana RODRIGUEZ SALVADOR"
                }
            ]
        ],
        "round 1-1": [
            [
                {
                    "country": "SUI",
                    "name": "Binta NDIAYE"
                },
                {
                    "country": "ESP",
                    "name": "Adriana RODRIGUEZ SALVADOR"
                }
            ]
        ],
        "final_winner": "Binta NDIAYE"
    },
    "POOL D": {
        "round 1-4": [
            [
                {
                    "country": "ESP",
                    "name": "Carla UBASART MASCARO"
                },
                {
                    "winner": "Carla UBASART MASCARO"
                }
            ],
            [
                {
                    "country": "SRB",
                    "name": "Kristina NISAVIC"
                },
                {
                    "country": "ITA",
                    "name": "Silvia PELLITTERI"
                },
                {
                    "winner": "Kristina NISAVIC"
                }
            ],
            [
                {
                    "country": "UKR",
                    "name": "Anastasiia CHYZHEVSKA"
                },
                {
                    "country": "EST",
                    "name": "Merit TARKUS"
                },
                {
                    "winner": "Anastasiia CHYZHEVSKA"
                }
            ],
            [
                {
                    "country": "BEL",
                    "name": "Luna VERFAILLIE"
                },
                {
                    "country": "HUN",
                    "name": "Titanilla ABRAHAM"
                },
                {
                    "winner": "Luna VERFAILLIE"
                }
            ]
        ],
        "round 1-2": [
            [
                {
                    "country": "ESP",
                    "name": "Carla UBASART MASCARO"
                },
                {
                    "country": "SRB",
                    "name": "Kristina NISAVIC"
                },
                {
                    "winner": "Carla UBASART MASCARO"
                }
            ],
            [
                {
                    "country": "UKR",
                    "name": "Anastasiia CHYZHEVSKA"
                },
                {
                    "country": "BEL",
                    "name": "Luna VERFAILLIE"
                },
                {
                    "winner": "Luna VERFAILLIE"
                }
            ]
        ],
        "round 1-1": [
            [
                {
                    "country": "ESP",
                    "name": "Carla UBASART MASCARO"
                },
                {
                    "country": "BEL",
                    "name": "Luna VERFAILLIE"
                }
            ]
        ],
        "final_winner": "Carla UBASART MASCARO"
    },
    "REPECHAGE": {
        "round 1-2": [
            [
                {
                    "country": "FRA",
                    "name": "Alya DE CARVALHO"
                },
                {
                    "country": "HUN",
                    "name": "Kitti KOVACS"
                },
                {
                    "winner": "Kitti KOVACS"
                }
            ],
            [
                {
                    "country": "ESP",
                    "name": "Adriana RODRIGUEZ SALVADOR"
                },
                {
                    "country": "BEL",
                    "name": "Luna VERFAILLIE"
                },
                {
                    "winner": "Adriana RODRIGUEZ SALVADOR"
                }
            ],
            [
                {
                    "country": "HUN",
                    "name": "Kitti KOVACS"
                },
                {
                    "country": "ESP",
                    "name": "Carla UBASART MASCARO"
                },
                {
                    "winner": "Kitti KOVACS"
                }
            ],
            [
                {
                    "country": "ESP",
                    "name": "Adriana RODRIGUEZ SALVADOR"
                },
                {
                    "country": "ESP",
                    "name": "Malin WILSON CLARET"
                },
                {
                    "winner": "Malin WILSON CLARET"
                }
            ],
            [
                {
                    "country": "HUN",
                    "name": "Kitti KOVACS"
                }
            ],
            [
                {
                    "country": "ESP",
                    "name": "Malin WILSON CLARET"
                }
            ]
        ],
        "final_winners": [
            "Kitti KOVACS",
            "Malin WILSON CLARET"
        ]
    },
    "SEMI-FINALS": {
        "round 1-2": [
            [
                {
                    "country": "ESP",
                    "name": "Malin WILSON CLARET"
                },
                {
                    "country": "SLO",
                    "name": "Nika TOMC"
                },
                {
                    "winner": "Nika TOMC"
                }
            ],
            [
                {
                    "country": "SUI",
                    "name": "Binta NDIAYE"
                },
                {
                    "country": "ESP",
                    "name": "Carla UBASART MASCARO"
                },
                {
                    "winner": "Binta NDIAYE"
                }
            ]
        ],
        "round 1-1": [
            [
                {
                    "country": "SLO",
                    "name": "Nika TOMC"
                },
                {
                    "country": "SUI",
                    "name": "Binta NDIAYE"
                }
            ]
        ],
        "final_winner": "Binta NDIAYE"
    }
}