{
    "POOL A": {
        "round 1-4": [
            [
                {
                    "country": "AZE",
                    "name": "Farid GARAYEV"
                },
                {
                    "winner": "Farid GARAYEV"
                }
            ],
            [
                {
                    "country": "TUR",
                    "name": "Alisan YILDIZ"
                },
                {
                    "country": "AZE",
                    "name": "Famil AZIZOV"
                },
                {
                    "winner": "Famil AZIZOV"
                }
            ],
            [
                {
                    "country": "UZB",
                    "name": "Amirkhon NIZOMADDINOV"
                },
                {
                    "country": "AZE",
                    "name": "Murad FATULLAYEV"
                },
                {
                    "winner": "Murad FATULLAYEV"
                }
            ],
            [
                {
                    "country": "AZE",
                    "name": "Gudrat YUSIF"
                },
                {
                    "country": "ISR",
                    "name": "Omer REICHER"
                },
                {
                    "winner": "Omer REICHER"
                }
            ]
        ],
        "round 1-2": [
            [
                {
                    "country": "AZE",
                    "name": "Farid GARAYEV"
                },
                {
                    "country": "AZE",
                    "name": "Famil AZIZOV"
                },
                {
                    "winner": "Farid GARAYEV"
                }
            ],
            [
                {
                    "country": "AZE",
                    "name": "Murad FATULLAYEV"
                },
                {
                    "country": "ISR",
                    "name": "Omer REICHER"
                },
                {
                    "winner": "Murad FATULLAYEV"
                }
            ]
        ],
        "round 1-1": [
            [
                {
                    "country": "AZE",
                    "name": "Farid GARAYEV"
                },
                {
                    "country": "AZE",
                    "name": "Murad FATULLAYEV"
                }
            ]
        ],
        "final_winner": "Farid GARAYEV"
    },
    "POOL B": {
        "round 1-4": [
            [
                {
                    "country": "AZE",
                    "name": "Aykhan MIRZAZADA"
                },
                {
                    "country": "DEN",
                    "name": "Marcus LANGE"
                },
                {
                    "winner": "Aykhan MIRZAZADA"
                }
            ],
            [
                {
                    "country": "AZE",
                    "name": "Aykhan ALAKBAROV"
                },
                {
                    "country": "KGZ",
                    "name": "Bakyt ISAEV"
                },
                {
                    "winner": "Aykhan ALAKBAROV"
                }
            ],
            [
                {
                    "country": "SLO",
                    "name": "Gal BLAZIC"
                },
                {
                    "country": "AZE",
                    "name": "Ibrahim ALIYEV"
                },
                {
                    "winner": "Gal BLAZIC"
                }
            ],
            [
                {
                    "country": "AZE",
                    "name": "Nemat ISAYEV"
                },
                {
                    "country": "SWE",
                    "name": "Samir POBLOCKI"
                },
                {
                    "winner": "Nemat ISAYEV"
                }
            ]
        ],
        "round 1-2": [
            [
                {
                    "country": "AZE",
                    "name": "Aykhan MIRZAZADA"
                },
                {
                    "country": "AZE",
                    "name": "Aykhan ALAKBAROV"
                },
                {
                    "winner": "Aykhan MIRZAZADA"
                }
            ],
            [
                {
                    "country": "SLO",
                    "name": "Gal BLAZIC"
                },
                {
                    "country": "AZE",
                    "name": "Nemat ISAYEV"
                },
                {
                    "winner": "Gal BLAZIC"
                }
            ]
        ],
        "round 1-1": [
            [
                {
                    "country": "AZE",
                    "name": "Aykhan MIRZAZADA"
                },
                {
                    "country": "SLO",
                    "name": "Gal BLAZIC"
                }
            ]
        ],
        "final_winner": "Aykhan MIRZAZADA"
    },
    "POOL C": {
        "round 1-4": [
            [
                {
                    "country": "AZE",
                    "name": "Mirkhalig ISKANDAROV"
                },
                {
                    "winner": "Mirkhalig ISKANDAROV"
                }
            ],
            [
                {
                    "country": "GEO",
                    "name": "Nika NANETASHVILI"
                },
                {
                    "country": "AZE",
                    "name": "Rasul ALIYEV"
                },
                {
                    "winner": "Nika NANETASHVILI"
                }
            ],
            [
                {
                    "country": "AZE",
                    "name": "Hasan HASANLI"
                },
                {
                    "country": "EST",
                    "name": "Filipp SHCHEKOTIN"
                },
                {
                    "winner": "Hasan HASANLI"
                }
            ],
            [
                {
                    "country": "TUR",
                    "name": "Yusuf Can UZUN"
                },
                {
                    "country": "AZE",
                    "name": "Telman ABDULLAYEV"
                },
                {
                    "winner": "Yusuf Can UZUN"
                }
            ]
        ],
        "round 1-2": [
            [
                {
                    "country": "AZE",
                    "name": "Mirkhalig ISKANDAROV"
                },
                {
                    "country": "GEO",
                    "name": "Nika NANETASHVILI"
                },
                {
                    "winner": "Mirkhalig ISKANDAROV"
                }
            ],
            [
                {
                    "country": "AZE",
                    "name": "Hasan HASANLI"
                },
                {
                    "country": "TUR",
                    "name": "Yusuf Can UZUN"
                },
                {
                    "winner": "Yusuf Can UZUN"
                }
            ]
        ],
        "round 1-1": [
            [
                {
                    "country": "AZE",
                    "name": "Mirkhalig ISKANDAROV"
                },
                {
                    "country": "TUR",
                    "name": "Yusuf Can UZUN"
                }
            ]
        ],
        "final_winner": "Mirkhalig ISKANDAROV"
    },
    "POOL D": {
        "round 1-4": [
            [
                {
                    "country": "POL",
                    "name": "Franciszek MICHALAK"
                },
                {
                    "winner": "Franciszek MICHALAK"
                }
            ],
            [
                {
                    "country": "AZE",
                    "name": "Samad ABDULAZIMLI"
                },
                {
                    "country": "POR",
                    "name": "Manuel ZORRETA"
                },
                {
                    "winner": "Manuel ZORRETA"
                }
            ],
            [
                {
                    "country": "KGZ",
                    "name": "Adis OROZMAMATOV"
                },
                {
                    "country": "AZE",
                    "name": "Zamin ALIYEV"
                },
                {
                    "winner": "Adis OROZMAMATOV"
                }
            ],
            [
                {
                    "country": "AZE",
                    "name": "Ramiz SADIKHOV"
                },
                {
                    "country": "GRE",
                    "name": "Marios KARIPIDIS"
                },
                {
                    "winner": "Ramiz SADIKHOV"
                }
            ]
        ],
        "round 1-2": [
            [
                {
                    "country": "POL",
                    "name": "Franciszek MICHALAK"
                },
                {
                    "country": "POR",
                    "name": "Manuel ZORRETA"
                },
                {
                    "winner": "Franciszek MICHALAK"
                }
            ],
            [
                {
                    "country": "KGZ",
                    "name": "Adis OROZMAMATOV"
                },
                {
                    "country": "AZE",
                    "name": "Ramiz SADIKHOV"
                },
                {
                    "winner": "Adis OROZMAMATOV"
                }
            ]
        ],
        "round 1-1": [
            [
                {
                    "country": "POL",
                    "name": "Franciszek MICHALAK"
                },
                {
                    "country": "KGZ",
                    "name": "Adis OROZMAMATOV"
                }
            ]
        ],
        "final_winner": "Franciszek MICHALAK"
    },
    "REPECHAGE": {
        "round 1-4": [
            [
                {
                    "country": "AZE",
                    "name": "Famil AZIZOV"
                },
                {
                    "winner": "Famil AZIZOV"
                }
            ],
            [
                {
                    "country": "DEN",
                    "name": "Marcus LANGE"
                },
                {
                    "country": "AZE",
                    "name": "Aykhan ALAKBAROV"
                },
                {
                    "winner": "Aykhan ALAKBAROV"
                }
            ],
            [
                {
                    "country": "GEO",
                    "name": "Nika NANETASHVILI"
                },
                {
                    "winner": "Nika NANETASHVILI"
                }
            ],
            [
                {
                    "country": "POR",
                    "name": "Manuel ZORRETA"
                },
                {
                    "winner": "Manuel ZORRETA"
                }
            ],
            [
                {
                    "country": "AZE",
                    "name": "Famil AZIZOV"
                },
                {
                    "country": "AZE",
                    "name": "Murad FATULLAYEV"
                },
                {
                    "winner": "Murad FATULLAYEV"
                }
            ],
            [
                {
                    "country": "AZE",
                    "name": "Aykhan ALAKBAROV"
                },
                {
                    "country": "SLO",
                    "name": "Gal BLAZIC"
                },
                {
                    "winner": "Gal BLAZIC"
                }
            ],
            [
                {
                    "country": "GEO",
                    "name": "Nika NANETASHVILI"
                },
                {
                    "country": "TUR",
                    "name": "Yusuf Can UZUN"
                },
                {
                    "winner": "Nika NANETASHVILI"
                }
            ],
            [
                {
                    "country": "POR",
                    "name": "Manuel ZORRETA"
                },
                {
                    "country": "KGZ",
                    "name": "Adis OROZMAMATOV"
                },
                {
                    "winner": "Adis OROZMAMATOV"
                }
            ]
        ],
        "round 1-2": [
            [
                {
                    "country": "AZE",
                    "name": "Murad FATULLAYEV"
                },
                {
                    "country": "SLO",
                    "name": "Gal BLAZIC"
                },
                {
                    "winner": "Murad FATULLAYEV"
                }
            ],
            [
                {
                    "country": "GEO",
                    "name": "Nika NANETASHVILI"
                },
                {
                    "country": "KGZ",
                    "name": "Adis OROZMAMATOV"
                },
                {
                    "winner": "Nika NANETASHVILI"
                }
            ],
            [
                {
                    "country": "AZE",
                    "name": "Murad FATULLAYEV"
                },
                {
                    "country": "POL",
                    "name": "Franciszek MICHALAK"
                },
                {
                    "winner": "Murad FATULLAYEV"
                }
            ],
            [
                {
                    "country": "GEO",
                    "name": "Nika NANETASHVILI"
                },
                {
                    "country": "AZE",
                    "name": "Aykhan MIRZAZADA"
                },
                {
                    "winner": "Aykhan MIRZAZADA"
                }
            ],
            [
                {
                    "country": "AZE",
                    "name": "Murad FATULLAYEV"
                }
            ],
            [
                {
                    "country": "AZE",
                    "name": "Aykhan MIRZAZADA"
                }
            ]
        ],
        "final_winners": [
            "Murad FATULLAYEV",
            "Aykhan MIRZAZADA"
        ]
    },
    "SEMI-FINALS": {
        "round 1-2": [
            [
                {
                    "country": "AZE",
                    "name": "Farid GARAYEV"
                },
                {
                    "country": "AZE",
                    "name": "Aykhan MIRZAZADA"
                },
                {
                    "winner": "Farid GARAYEV"
                }
            ],
            [
                {
                    "country": "AZE",
                    "name": "Mirkhalig ISKANDAROV"
                },
                {
                    "country": "POL",
                    "name": "Franciszek MICHALAK"
                },
                {
                    "winner": "Mirkhalig ISKANDAROV"
                }
            ]
        ],
        "round 1-1": [
            [
                {
                    "country": "AZE",
                    "name": "Farid GARAYEV"
                },
                {
                    "country": "AZE",
                    "name": "Mirkhalig ISKANDAROV"
                }
            ]
        ],
        "final_winner": "Mirkhalig ISKANDAROV"
    }
}