{
    "POOL A": {
        "round 1-4": [
            [
                {
                    "country": "ITA",
                    "name": "Michela TERRANOVA"
                },
                {
                    "winner": "Michela TERRANOVA"
                }
            ],
            [
                {
                    "country": "MKD",
                    "name": "Liljana NEDANOVSKA"
                },
                {
                    "country": "SRB",
                    "name": "Dunja SADIKU"
                },
                {
                    "winner": "Liljana NEDANOVSKA"
                }
            ],
            [
                {
                    "country": "TUR",
                    "name": "Elif AGAR"
                },
                {
                    "winner": "Elif AGAR"
                }
            ],
            [
                {
                    "country": "IJF",
                    "name": "Daria KUZMINA"
                },
                {
                    "winner": "Daria KUZMINA"
                }
            ]
        ],
        "round 1-2": [
            [
                {
                    "country": "ITA",
                    "name": "Michela TERRANOVA"
                },
                {
                    "country": "MKD",
                    "name": "Liljana NEDANOVSKA"
                },
                {
                    "winner": "Michela TERRANOVA"
                }
            ],
            [
                {
                    "country": "TUR",
                    "name": "Elif AGAR"
                },
                {
                    "country": "IJF",
                    "name": "Daria KUZMINA"
                },
                {
                    "winner": "Daria KUZMINA"
                }
            ]
        ],
        "round 1-1": [
            [
                {
                    "country": "ITA",
                    "name": "Michela TERRANOVA"
                },
                {
                    "country": "IJF",
                    "name": "Daria KUZMINA"
                }
            ]
        ],
        "final_winner": "Michela TERRANOVA"
    },
    "POOL B": {
        "round 1-4": [
            [
                {
                    "country": "ALB",
                    "name": "Erisa BRAHIMAJ"
                },
                {
                    "winner": "Erisa BRAHIMAJ"
                }
            ],
            [
                {
                    "country": "GBR",
                    "name": "Kenady RAINE"
                },
                {
                    "country": "GER",
                    "name": "Leonie WICKERT"
                },
                {
                    "winner": "Leonie WICKERT"
                }
            ],
            [
                {
                    "country": "CYP",
                    "name": "Marina AZINOU"
                },
                {
                    "winner": "Marina AZINOU"
                }
            ],
            [
                {
                    "country": "IJF",
                    "name": "Evelina BOSIEK"
                },
                {
                    "country": "GRE",
                    "name": "Evangelia GAVALA"
                },
                {
                    "winner": "Evelina BOSIEK"
                }
            ]
        ],
        "round 1-2": [
            [
                {
                    "country": "ALB",
                    "name": "Erisa BRAHIMAJ"
                },
                {
                    "country": "GER",
                    "name": "Leonie WICKERT"
                },
                {
                    "winner": "Erisa BRAHIMAJ"
                }
            ],
            [
                {
                    "country": "CYP",
                    "name": "Marina AZINOU"
                },
                {
                    "country": "IJF",
                    "name": "Evelina BOSIEK"
                },
                {
                    "winner": "Evelina BOSIEK"
                }
            ]
        ],
        "round 1-1": [
            [
                {
                    "country": "ALB",
                    "name": "Erisa BRAHIMAJ"
                },
                {
                    "country": "IJF",
                    "name": "Evelina BOSIEK"
                }
            ]
        ],
        "final_winner": "Evelina BOSIEK"
    },
    "POOL C": {
        "round 1-4": [
            [
                {
                    "country": "GBR",
                    "name": "Madeleine BIRRI"
                },
                {
                    "winner": "Madeleine BIRRI"
                }
            ],
            [
                {
                    "country": "TUR",
                    "name": "Zeynep OZTURK"
                },
                {
                    "country": "CRO",
                    "name": "Maria SKOMERSIC"
                },
                {
                    "winner": "Zeynep OZTURK"
                }
            ],
            [
                {
                    "country": "GER",
                    "name": "Helene RIEGERT"
                },
                {
                    "winner": "Helene RIEGERT"
                }
            ],
            [
                {
                    "country": "SRB",
                    "name": "Djurdja VUKADINOVIC"
                },
                {
                    "country": "IJF",
                    "name": "Elvida GUREVA"
                },
                {
                    "winner": "Elvida GUREVA"
                }
            ]
        ],
        "round 1-2": [
            [
                {
                    "country": "GBR",
                    "name": "Madeleine BIRRI"
                },
                {
                    "country": "TUR",
                    "name": "Zeynep OZTURK"
                },
                {
                    "winner": "Madeleine BIRRI"
                }
            ],
            [
                {
                    "country": "GER",
                    "name": "Helene RIEGERT"
                },
                {
                    "country": "IJF",
                    "name": "Elvida GUREVA"
                },
                {
                    "winner": "Elvida GUREVA"
                }
            ]
        ],
        "round 1-1": [
            [
                {
                    "country": "GBR",
                    "name": "Madeleine BIRRI"
                },
                {
                    "country": "IJF",
                    "name": "Elvida GUREVA"
                }
            ]
        ],
        "final_winner": "Elvida GUREVA"
    },
    "POOL D": {
        "round 1-4": [
            [
                {
                    "country": "POL",
                    "name": "Julia BULANDA"
                },
                {
                    "winner": "Julia BULANDA"
                }
            ],
            [
                {
                    "country": "ALB",
                    "name": "Desara NDOCI"
                },
                {
                    "country": "IJF",
                    "name": "Aleksandra SHESTOPALOVA"
                },
                {
                    "winner": "Aleksandra SHESTOPALOVA"
                }
            ],
            [
                {
                    "country": "LIE",
                    "name": "Lea WYSS"
                },
                {
                    "winner": "Lea WYSS"
                }
            ],
            [
                {
                    "country": "ITA",
                    "name": "Martina CAPEZZUTO"
                },
                {
                    "country": "BIH",
                    "name": "Nikolina JASIKOVAC"
                },
                {
                    "winner": "Martina CAPEZZUTO"
                }
            ]
        ],
        "round 1-2": [
            [
                {
                    "country": "POL",
                    "name": "Julia BULANDA"
                },
                {
                    "country": "IJF",
                    "name": "Aleksandra SHESTOPALOVA"
                },
                {
                    "winner": "Aleksandra SHESTOPALOVA"
                }
            ],
            [
                {
                    "country": "LIE",
                    "name": "Lea WYSS"
                },
                {
                    "country": "ITA",
                    "name": "Martina CAPEZZUTO"
                },
                {
                    "winner": "Lea WYSS"
                }
            ]
        ],
        "round 1-1": [
            [
                {
                    "country": "IJF",
                    "name": "Aleksandra SHESTOPALOVA"
                },
                {
                    "country": "LIE",
                    "name": "Lea WYSS"
                }
            ]
        ],
        "final_winner": "Aleksandra SHESTOPALOVA"
    },
    "REPECHAGE": {
        "round 1-4": [
            [
                {
                    "country": "MKD",
                    "name": "Liljana NEDANOVSKA"
                },
                {
                    "winner": "Liljana NEDANOVSKA"
                }
            ],
            [
                {
                    "country": "GRE",
                    "name": "Evangelia GAVALA"
                },
                {
                    "country": "CYP",
                    "name": "Marina AZINOU"
                },
                {
                    "winner": "Marina AZINOU"
                }
            ],
            [
                {
                    "country": "SRB",
                    "name": "Djurdja VUKADINOVIC"
                },
                {
                    "country": "GER",
                    "name": "Helene RIEGERT"
                },
                {
                    "winner": "Helene RIEGERT"
                }
            ],
            [
                {
                    "country": "ALB",
                    "name": "Desara NDOCI"
                },
                {
                    "country": "POL",
                    "name": "Julia BULANDA"
                },
                {
                    "winner": "Julia BULANDA"
                }
            ],
            [
                {
                    "country": "MKD",
                    "name": "Liljana NEDANOVSKA"
                },
                {
                    "country": "IJF",
                    "name": "Daria KUZMINA"
                },
                {
                    "winner": "Daria KUZMINA"
                }
            ],
            [
                {
                    "country": "CYP",
                    "name": "Marina AZINOU"
                },
                {
                    "country": "ALB",
                    "name": "Erisa BRAHIMAJ"
                },
                {
                    "winner": "Marina AZINOU"
                }
            ],
            [
                {
                    "country": "GER",
                    "name": "Helene RIEGERT"
                },
                {
                    "country": "GBR",
                    "name": "Madeleine BIRRI"
                },
                {
                    "winner": "Helene RIEGERT"
                }
            ],
            [
                {
                    "country": "POL",
                    "name": "Julia BULANDA"
                },
                {
                    "country": "LIE",
                    "name": "Lea WYSS"
                },
                {
                    "winner": "Lea WYSS"
                }
            ]
        ],
        "round 1-2": [
            [
                {
                    "country": "IJF",
                    "name": "Daria KUZMINA"
                },
                {
                    "country": "CYP",
                    "name": "Marina AZINOU"
                },
                {
                    "winner": "Daria KUZMINA"
                }
            ],
            [
                {
                    "country": "GER",
                    "name": "Helene RIEGERT"
                },
                {
                    "country": "LIE",
                    "name": "Lea WYSS"
                },
                {
                    "winner": "Helene RIEGERT"
                }
            ],
            [
                {
                    "country": "IJF",
                    "name": "Daria KUZMINA"
                },
                {
                    "country": "IJF",
                    "name": "Aleksandra SHESTOPALOVA"
                },
                {
                    "winner": "Aleksandra SHESTOPALOVA"
                }
            ],
            [
                {
                    "country": "GER",
                    "name": "Helene RIEGERT"
                },
                {
                    "country": "IJF",
                    "name": "Evelina BOSIEK"
                },
                {
                    "winner": "Helene RIEGERT"
                }
            ],
            [
                {
                    "country": "IJF",
                    "name": "Aleksandra SHESTOPALOVA"
                }
            ],
            [
                {
                    "country": "GER",
                    "name": "Helene RIEGERT"
                }
            ]
        ],
        "final_winners": [
            "Aleksandra SHESTOPALOVA",
            "Helene RIEGERT"
        ]
    },
    "SEMI-FINALS": {
        "round 1-2": [
            [
                {
                    "country": "ITA",
                    "name": "Michela TERRANOVA"
                },
                {
                    "country": "IJF",
                    "name": "Evelina BOSIEK"
                },
                {
                    "winner": "Michela TERRANOVA"
                }
            ],
            [
                {
                    "country": "IJF",
                    "name": "Elvida GUREVA"
                },
                {
                    "country": "IJF",
                    "name": "Aleksandra SHESTOPALOVA"
                },
                {
                    "winner": "Elvida GUREVA"
                }
            ]
        ],
        "round 1-1": [
            [
                {
                    "country": "ITA",
                    "name": "Michela TERRANOVA"
                },
                {
                    "country": "IJF",
                    "name": "Elvida GUREVA"
                }
            ]
        ],
        "final_winner": "Michela TERRANOVA"
    }
}