{
    "POOL A": {
        "round 1-2": [
            [
                {
                    "country": "GER",
                    "name": "Kilian KAPPELMEIER"
                },
                {
                    "winner": "Kilian KAPPELMEIER"
                }
            ],
            [
                {
                    "country": "FRA",
                    "name": "Marc SOUMAHORO"
                },
                {
                    "country": "FRA",
                    "name": "Benjamin JENNER"
                },
                {
                    "winner": "Marc SOUMAHORO"
                }
            ]
        ],
        "round 1-1": [
            [
                {
                    "country": "GER",
                    "name": "Kilian KAPPELMEIER"
                },
                {
                    "country": "FRA",
                    "name": "Marc SOUMAHORO"
                }
            ]
        ],
        "final_winner": "Kilian KAPPELMEIER"
    },
    "POOL B": {
        "round 1-2": [
            [
                {
                    "country": "FRA",
                    "name": "Maxence BORDIN"
                },
                {
                    "country": "JPN",
                    "name": "Riku HIRAMI"
                },
                {
                    "winner": "Riku HIRAMI"
                }
            ],
            [
                {
                    "country": "FRA",
                    "name": "Yann RIGAUD"
                },
                {
                    "country": "GER",
                    "name": "Pierre EDERER"
                },
                {
                    "winner": "Yann RIGAUD"
                }
            ]
        ],
        "round 1-1": [
            [
                {
                    "country": "JPN",
                    "name": "Riku HIRAMI"
                },
                {
                    "country": "FRA",
                    "name": "Yann RIGAUD"
                }
            ]
        ],
        "final_winner": "Riku HIRAMI"
    },
    "POOL C": {
        "round 1-2": [
            [
                {
                    "country": "FRA",
                    "name": "Mathias ANGLIONIN"
                },
                {
                    "winner": "Mathias ANGLIONIN"
                }
            ],
            [
                {
                    "country": "FRA",
                    "name": "Fares MEKHOUKH"
                },
                {
                    "country": "GER",
                    "name": "Mortaza SUHA"
                },
                {
                    "winner": "Fares MEKHOUKH"
                }
            ]
        ],
        "round 1-1": [
            [
                {
                    "country": "FRA",
                    "name": "Mathias ANGLIONIN"
                },
                {
                    "country": "FRA",
                    "name": "Fares MEKHOUKH"
                }
            ]
        ],
        "final_winner": "Mathias ANGLIONIN"
    },
    "POOL D": {
        "round 1-2": [
            [
                {
                    "country": "NED",
                    "name": "Silvan BULTHUIS"
                },
                {
                    "country": "FRA",
                    "name": "Hugo LUTZ"
                },
                {
                    "winner": "Silvan BULTHUIS"
                }
            ],
            [
                {
                    "country": "NED",
                    "name": "Joes SCHELL"
                },
                {
                    "country": "FRA",
                    "name": "Kris Oliver SIEWE DJIEKAM"
                },
                {
                    "winner": "Joes SCHELL"
                }
            ]
        ],
        "round 1-1": [
            [
                {
                    "country": "NED",
                    "name": "Silvan BULTHUIS"
                },
                {
                    "country": "NED",
                    "name": "Joes SCHELL"
                }
            ]
        ],
        "final_winner": "Joes SCHELL"
    },
    "REPECHAGE": {
        "round 1-4": [
            [
                {
                    "country": "FRA",
                    "name": "Marc SOUMAHORO"
                },
                {
                    "winner": "Marc SOUMAHORO"
                }
            ],
            [
                {
                    "country": "FRA",
                    "name": "Maxence BORDIN"
                },
                {
                    "country": "FRA",
                    "name": "Yann RIGAUD"
                },
                {
                    "winner": "Maxence BORDIN"
                }
            ],
            [
                {
                    "country": "FRA",
                    "name": "Fares MEKHOUKH"
                },
                {
                    "winner": "Fares MEKHOUKH"
                }
            ],
            [
                {
                    "country": "FRA",
                    "name": "Kris Oliver SIEWE DJIEKAM"
                },
                {
                    "country": "NED",
                    "name": "Silvan BULTHUIS"
                },
                {
                    "winner": "Kris Oliver SIEWE DJIEKAM"
                }
            ]
        ],
        "round 1-2": [
            [
                {
                    "country": "FRA",
                    "name": "Marc SOUMAHORO"
                },
                {
                    "country": "FRA",
                    "name": "Maxence BORDIN"
                },
                {
                    "winner": "Maxence BORDIN"
                }
            ],
            [
                {
                    "country": "FRA",
                    "name": "Fares MEKHOUKH"
                },
                {
                    "country": "FRA",
                    "name": "Kris Oliver SIEWE DJIEKAM"
                },
                {
                    "winner": "Fares MEKHOUKH"
                }
            ],
            [
                {
                    "country": "FRA",
                    "name": "Maxence BORDIN"
                },
                {
                    "country": "FRA",
                    "name": "Mathias ANGLIONIN"
                },
                {
                    "winner": "Mathias ANGLIONIN"
                }
            ],
            [
                {
                    "country": "FRA",
                    "name": "Fares MEKHOUKH"
                },
                {
                    "country": "JPN",
                    "name": "Riku HIRAMI"
                },
                {
                    "winner": "Fares MEKHOUKH"
                }
            ],
            [
                {
                    "country": "FRA",
                    "name": "Mathias ANGLIONIN"
                }
            ],
            [
                {
                    "country": "FRA",
                    "name": "Fares MEKHOUKH"
                }
            ]
        ],
        "final_winners": [
            "Mathias ANGLIONIN",
            "Fares MEKHOUKH"
        ]
    },
    "SEMI-FINALS": {
        "round 1-2": [
            [
                {
                    "country": "GER",
                    "name": "Kilian KAPPELMEIER"
                },
                {
                    "country": "JPN",
                    "name": "Riku HIRAMI"
                },
                {
                    "winner": "Kilian KAPPELMEIER"
                }
            ],
            [
                {
                    "country": "FRA",
                    "name": "Mathias ANGLIONIN"
                },
                {
                    "country": "NED",
                    "name": "Joes SCHELL"
                },
                {
                    "winner": "Joes SCHELL"
                }
            ]
        ],
        "round 1-1": [
            [
                {
                    "country": "GER",
                    "name": "Kilian KAPPELMEIER"
                },
                {
                    "country": "NED",
                    "name": "Joes SCHELL"
                }
            ]
        ],
        "final_winner": "Kilian KAPPELMEIER"
    }
}