{
    "POOL A": {
        "round 1-1": [
            [
                {
                    "country": "KGZ",
                    "name": "Akmarzhan TURDAZHIEVA"
                },
                {
                    "country": "UZB",
                    "name": "Yulianna SHUBLADZE"
                }
            ]
        ],
        "final_winner": "Akmarzhan TURDAZHIEVA"
    },
    "POOL B": {
        "round 1-1": [
            [
                {
                    "country": "UZB",
                    "name": "Marjona KUCHIMOVA"
                },
                {
                    "country": "KAZ",
                    "name": "Snezhana YAKUBOVA"
                }
            ]
        ],
        "final_winner": "Marjona KUCHIMOVA"
    },
    "POOL C": {
        "round 1-1": [
            [
                {
                    "country": "KAZ",
                    "name": "Ruslana MAKHATOVA"
                },
                {
                    "country": "UZB",
                    "name": "Zarinz BOBONAZROVA"
                }
            ]
        ],
        "final_winner": "Ruslana MAKHATOVA"
    },
    "POOL D": {
        "round 1-1": [
            [
                {
                    "country": "UZB",
                    "name": "Khurshidakhon OSLONBOEVA"
                },
                {
                    "country": "UZB",
                    "name": "Xayrijamol TUKHTAMISHOVA"
                }
            ]
        ],
        "final_winner": "Khurshidakhon OSLONBOEVA"
    },
    "REPECHAGE": {
        "round 1-2": [
            [
                {
                    "country": "UZB",
                    "name": "Yulianna SHUBLADZE"
                },
                {
                    "country": "KAZ",
                    "name": "Snezhana YAKUBOVA"
                },
                {
                    "winner": "Snezhana YAKUBOVA"
                }
            ],
            [
                {
                    "country": "UZB",
                    "name": "Zarinz BOBONAZROVA"
                },
                {
                    "country": "UZB",
                    "name": "Xayrijamol TUKHTAMISHOVA"
                },
                {
                    "winner": "Zarinz BOBONAZROVA"
                }
            ],
            [
                {
                    "country": "KAZ",
                    "name": "Snezhana YAKUBOVA"
                },
                {
                    "country": "UZB",
                    "name": "Khurshidakhon OSLONBOEVA"
                },
                {
                    "winner": "Snezhana YAKUBOVA"
                }
            ],
            [
                {
                    "country": "UZB",
                    "name": "Zarinz BOBONAZROVA"
                },
                {
                    "country": "UZB",
                    "name": "Marjona KUCHIMOVA"
                },
                {
                    "winner": "Marjona KUCHIMOVA"
                }
            ],
            [
                {
                    "country": "KAZ",
                    "name": "Snezhana YAKUBOVA"
                }
            ],
            [
                {
                    "country": "UZB",
                    "name": "Marjona KUCHIMOVA"
                }
            ]
        ],
        "final_winners": [
            "Snezhana YAKUBOVA",
            "Marjona KUCHIMOVA"
        ]
    },
    "SEMI-FINALS": {
        "round 1-2": [
            [
                {
                    "country": "KGZ",
                    "name": "Akmarzhan TURDAZHIEVA"
                },
                {
                    "country": "UZB",
                    "name": "Marjona KUCHIMOVA"
                },
                {
                    "winner": "Akmarzhan TURDAZHIEVA"
                }
            ],
            [
                {
                    "country": "KAZ",
                    "name": "Ruslana MAKHATOVA"
                },
                {
                    "country": "UZB",
                    "name": "Khurshidakhon OSLONBOEVA"
                },
                {
                    "winner": "Ruslana MAKHATOVA"
                }
            ]
        ],
        "round 1-1": [
            [
                {
                    "country": "KGZ",
                    "name": "Akmarzhan TURDAZHIEVA"
                },
                {
                    "country": "KAZ",
                    "name": "Ruslana MAKHATOVA"
                }
            ]
        ],
        "final_winner": "Akmarzhan TURDAZHIEVA"
    }
}